{
	"info": {
		"name": "Bistro K10",
		"location": {
			"lat": 51.321952,
			"long": 9.503411
		}
	},
	"validity": {
		"from": "2017-10-30T00:00:00.000Z",
		"until": "2017-11-04T00:00:00.000Z"
	},
	"currency": "€",
	"meals": {
		"Angebot 1": {
			"1": {
				"name": "Zartes Putengeschnetzeltes mit toskanischem Gemüse",
				"attributes": [
					"30"
				],
				"price": {
					"student": 3.3,
					"employee": 4.6,
					"visitor": 5.5
				},
				"vitalInfo": null
			},
			"2": {
				"name": "Feiertag - Heute bleiben unsere Einrichtungen geschlossen",
				"attributes": [],
				"price": {
					"student": 0,
					"employee": 1.3,
					"visitor": 2.2
				},
				"vitalInfo": null
			},
			"3": {
				"name": "Frisch gebratenes Hähnchenbrustschnitzel auf Pfifferlingrahmsauce",
				"attributes": [
					"30",
					"32",
					"36"
				],
				"price": {
					"student": 3.5,
					"employee": 4.8,
					"visitor": 5.7
				},
				"vitalInfo": null
			},
			"4": {
				"name": "Geschnetzeltes vom Schwein nach Züricher Art",
				"attributes": [
					"1",
					"30",
					"36",
					"S"
				],
				"price": {
					"student": 3.4,
					"employee": 4.7,
					"visitor": 5.6
				},
				"vitalInfo": null
			},
			"5": {
				"name": "Hausgemachtes Rinderhacksteak mit tomatisierter Bratenjus",
				"attributes": [
					"30",
					"32",
					"35",
					"39",
					"R"
				],
				"price": {
					"student": 3.5,
					"employee": 4.8,
					"visitor": 5.7
				},
				"vitalInfo": null
			}
		},
		"Angebot 2": {
			"1": {
				"name": "Italienische Tagliatelle mit feiner Gemüsebolognese",
				"attributes": [
					"V",
					"30",
					"38"
				],
				"price": {
					"student": 2.8,
					"employee": 4.1,
					"visitor": 5
				},
				"vitalInfo": null
			},
			"2": null,
			"3": {
				"name": "Gemüsecurry mit Kokosmilch und Thaicurry im Langkornreisbett",
				"attributes": [
					"V"
				],
				"price": {
					"student": 2.7,
					"employee": 4,
					"visitor": 4.9
				},
				"vitalInfo": null
			},
			"4": {
				"name": "Geschöpfte Tortellini mit Spinat-Ricotta-Füllung in Schnittlauchsauce",
				"attributes": [
					"F",
					"1",
					"30",
					"36",
					"38"
				],
				"price": {
					"student": 3.4,
					"employee": 4.7,
					"visitor": 5.6
				},
				"vitalInfo": null
			},
			"5": {
				"name": "Backfrischer Brokkoli-Pfannkuchen an Pfeffer-Schmanddip",
				"attributes": [
					"F",
					"30",
					"32",
					"36"
				],
				"price": {
					"student": 2.7,
					"employee": 4,
					"visitor": 4.9
				},
				"vitalInfo": null
			}
		},
		"Angebot 3 solange der Vorrat reicht": {
			"1": {
				"name": "Goldgelb gebackene Kartoffeltaschen mit Frischkäse gefüllt an fruchtiger Tomatensauce",
				"attributes": [
					"F",
					"30",
					"36"
				],
				"price": {
					"student": 3,
					"employee": 4.3,
					"visitor": 5.2
				},
				"vitalInfo": null
			},
			"2": null,
			"3": {
				"name": "Gebratenes Filet von der Lachsforelle auf Rahmspinat",
				"attributes": [
					"1",
					"30",
					"33"
				],
				"price": {
					"student": 5,
					"employee": 6.3,
					"visitor": 7.2
				},
				"vitalInfo": null
			},
			"4": {
				"name": "Ofenfrischer Flammkuchen mit Apfel, Kürbis und roten Zwiebeln",
				"attributes": [
					"F",
					"30",
					"36",
					"38"
				],
				"price": {
					"student": 4,
					"employee": 5.3,
					"visitor": 6.2
				},
				"vitalInfo": null
			},
			"5": {
				"name": "Nordischer Fischburger mit frischem Salat, saurer Gurke und Röstzwiebeln",
				"attributes": [
					"1",
					"9",
					"30",
					"32",
					"33",
					"36",
					"39",
					"40"
				],
				"price": {
					"student": 3.5,
					"employee": 4.8,
					"visitor": 5.7
				},
				"vitalInfo": null
			}
		}
	}
}
