{
	"info": {
		"name": "Mensa Menzelstraße",
		"location": {
			"lat": 51.305234,
			"long": 9.489587
		}
	},
	"validity": {
		"from": "2017-10-02T00:00:00.000Z",
		"until": "2017-10-06T00:00:00.000Z"
	},
	"currency": "€",
	"meals": {
		"Essen 1": {
			"1": {
				"name": "Blumenkohl-Käse-Medaillon an Sauce Bérnaise",
				"attributes": [
					"F",
					"30",
					"32",
					"36",
					"38"
				],
				"price": {
					"student": 1.9,
					"employee": 3.2,
					"visitor": 4.1
				},
				"vitalInfo": null
			},
			"2": {
				"name": "Feiertag - Heute bleiben unsere Einrichtungen geschlossen",
				"attributes": [],
				"price": {
					"student": 1.9,
					"employee": 3.2,
					"visitor": 4.1
				},
				"vitalInfo": null
			},
			"3": {
				"name": "Couscouspfanne mit knackigem Gemüse an rotem Linsendip",
				"attributes": [
					"V",
					"3",
					"30",
					"39",
					"40"
				],
				"price": {
					"student": 1.9,
					"employee": 3.2,
					"visitor": 4.1
				},
				"vitalInfo": null
			},
			"4": {
				"name": "Spaghetti mit feinem Karottenpesto",
				"attributes": [
					"V",
					"30",
					"37"
				],
				"price": {
					"student": 1.8,
					"employee": 3.1,
					"visitor": 4
				},
				"vitalInfo": null
			},
			"5": {
				"name": "Hausgemachter Süßkartoffelstampf auf Balsamico-Linsen",
				"attributes": [
					"V",
					"1",
					"3",
					"35"
				],
				"price": {
					"student": 1.9,
					"employee": 3.2,
					"visitor": 4.1
				},
				"vitalInfo": null
			}
		},
		"Essen 2": {
			"1": {
				"name": "Mini-Hackfleischbällchen auf Western-Tomatensauce",
				"attributes": [
					"1",
					"30",
					"32",
					"R",
					"S"
				],
				"price": {
					"student": 2.3,
					"employee": 3.6,
					"visitor": 4.5
				},
				"vitalInfo": null
			},
			"2": null,
			"3": {
				"name": "Hähnchenbrust mit Petersilienpesto ummantelt auf Béchamelsauce",
				"attributes": [
					"1",
					"2",
					"30",
					"36",
					"37"
				],
				"price": {
					"student": 2.5,
					"employee": 3.8,
					"visitor": 4.7
				},
				"vitalInfo": null
			},
			"4": {
				"name": "Gebratene Geflügel-Currywurst mit Ketchupsauce",
				"attributes": [
					"1",
					"36",
					"38",
					"39",
					"R"
				],
				"price": {
					"student": 2.3,
					"employee": 3.6,
					"visitor": 4.5
				},
				"vitalInfo": null
			},
			"5": {
				"name": "Gefülltes hessisches Kraut auf weißer Sauce",
				"attributes": [
					"1",
					"30",
					"32",
					"36",
					"39",
					"S"
				],
				"price": {
					"student": 2.4,
					"employee": 3.7,
					"visitor": 4.6
				},
				"vitalInfo": null
			}
		}
	}
}
